bin_formats.py
pastebin.py
NaNbin-0.0.1.dist-info/METADATA
NaNbin-0.0.1.dist-info/WHEEL
NaNbin-0.0.1.dist-info/top_level.txt
NaNbin-0.0.1.dist-info/RECORD
