Metadata-Version: 2.1
Name: NaNbin
Version: 0.0.1
Summary: A small package to create pastes on Pastebin with the Pastebin API
Home-page: UNKNOWN
Author: copycat666
License: UNKNOWN
Platform: UNKNOWN
Requires-Dist: requests
